{
  "name": "Q4: Named mortal Occultists",
  "img": "systems/againstthedarkconspiracy/assets/roll_tables/operational-answers.svg",
  "description": "What’s the threat the Operators want to face?\nNamed mortal Occultists\nWhat activity are they engaged in?",
  "results": [
    {
      "type": 0,
      "weight": 1,
      "range": [
        1,
        1
      ],
      "drawn": false,
      "documentCollection": "",
      "_id": "kK9DKpv8WFAEXTzJ",
      "text": "Preparing a ritual (which might include a sacrifice)",
      "img": "systems/againstthedarkconspiracy/assets/roll_tables/operational-answers.svg",
      "documentId": null,
      "flags": {},
      "_key": "!tables.results!YA1zoUkC7ODCUDDu.kK9DKpv8WFAEXTzJ"
    },
    {
      "type": 0,
      "weight": 1,
      "range": [
        2,
        2
      ],
      "drawn": false,
      "documentCollection": "",
      "_id": "AN5e020bHdaEItYA",
      "text": "Collecting or stealing occult material or an artefact",
      "img": "systems/againstthedarkconspiracy/assets/roll_tables/operational-answers.svg",
      "documentId": null,
      "flags": {},
      "_key": "!tables.results!YA1zoUkC7ODCUDDu.AN5e020bHdaEItYA"
    },
    {
      "type": 0,
      "weight": 1,
      "range": [
        3,
        3
      ],
      "drawn": false,
      "documentCollection": "",
      "_id": "t3li1D95UjVFMV5F",
      "text": "Preparing an attack on another group or faction",
      "img": "systems/againstthedarkconspiracy/assets/roll_tables/operational-answers.svg",
      "documentId": null,
      "flags": {},
      "_key": "!tables.results!YA1zoUkC7ODCUDDu.t3li1D95UjVFMV5F"
    },
    {
      "type": 0,
      "weight": 1,
      "range": [
        4,
        4
      ],
      "drawn": false,
      "documentCollection": "",
      "_id": "vMeN8URv5ei78yls",
      "text": "Searching for, or researching, something",
      "img": "systems/againstthedarkconspiracy/assets/roll_tables/operational-answers.svg",
      "documentId": null,
      "flags": {},
      "_key": "!tables.results!YA1zoUkC7ODCUDDu.vMeN8URv5ei78yls"
    },
    {
      "type": 0,
      "weight": 1,
      "range": [
        5,
        5
      ],
      "drawn": false,
      "documentCollection": "",
      "_id": "ThdIVrVzG6F27xmw",
      "text": "Recruiting 'innocents’ to the Conspiracy",
      "img": "systems/againstthedarkconspiracy/assets/roll_tables/operational-answers.svg",
      "documentId": null,
      "flags": {},
      "_key": "!tables.results!YA1zoUkC7ODCUDDu.ThdIVrVzG6F27xmw"
    },
    {
      "type": 0,
      "weight": 1,
      "range": [
        6,
        6
      ],
      "drawn": false,
      "documentCollection": "",
      "_id": "0jS7pb5IfDTFqOng",
      "text": "Meeting their Conspiracy handler",
      "img": "systems/againstthedarkconspiracy/assets/roll_tables/operational-answers.svg",
      "documentId": null,
      "flags": {},
      "_key": "!tables.results!YA1zoUkC7ODCUDDu.0jS7pb5IfDTFqOng"
    }
  ],
  "formula": "1d6",
  "replacement": true,
  "displayRoll": false,
  "flags": {
    "core": {
      "sourceId": "RollTable.x4y3kw92bmHRIMEc"
    }
  },
  "_stats": {
    "systemId": "custom-system-builder",
    "systemVersion": "2.3.0",
    "coreVersion": "10.291",
    "createdTime": 1686356240631,
    "modifiedTime": 1691090688031,
    "lastModifiedBy": "6UEkwTAOmwQ2wA1W"
  },
  "folder": null,
  "sort": 0,
  "ownership": {
    "default": 0,
    "6UEkwTAOmwQ2wA1W": 3
  },
  "_id": "YA1zoUkC7ODCUDDu",
  "_key": "!tables!YA1zoUkC7ODCUDDu"
}
